README.md
setup.cfg
setup.py
vismit/PasswordGenerator.py
vismit/__init__.py
vismit_python.egg-info/PKG-INFO
vismit_python.egg-info/SOURCES.txt
vismit_python.egg-info/dependency_links.txt
vismit_python.egg-info/not-zip-safe
vismit_python.egg-info/top_level.txt