Metadata-Version: 1.0
Name: vismit-python
Version: 1.0
Summary: Password generator
Home-page: https://github.com/TheDnM/vismit-python
Author: Aman Roy, Aditya Ray
Author-email: royaman8757@gmail.com, adiray5144@gmail.com
License: MIT
Platform: UNKNOWN
